Metadata-Version: 2.3
Name: aws-healthomics-tools
Version: 0.13.1
Summary: Tools for working with the AWS HealthOmics Service
License: Apache-2.0
Author: Amazon Web Services
Requires-Python: >=3.10,<4.0
Classifier: License :: OSI Approved :: Apache Software License
Classifier: Programming Language :: Python :: 3
Classifier: Programming Language :: Python :: 3.10
Classifier: Programming Language :: Python :: 3.11
Classifier: Programming Language :: Python :: 3.12
Classifier: Programming Language :: Python :: 3.13
Requires-Dist: bokeh (>=3.5.1,<4.0.0)
Requires-Dist: boto3 (>=1.37.36,<2.0.0)
Requires-Dist: boto3-stubs (>=1.37.36,<2.0.0)
Requires-Dist: botocore-stubs (>=1.37.36,<2.0.0)
Requires-Dist: docopt (>=0.6.2,<0.7.0)
Requires-Dist: mypy-boto3-omics (>=1.37.36,<2.0.0)
Requires-Dist: pandas (>=2.2.2,<3.0.0)
Requires-Dist: pillow (>=11.3.0)
Requires-Dist: python-dateutil (>=2.8.2,<3.0.0)
Requires-Dist: s3transfer (>=0.14.0)
Requires-Dist: tornado (>=6.5.0)
Project-URL: Repository, https://github.com/awslabs/amazon-omics-tools
